{
  "id": null,
  "title": "Application Metrics",
  "tags": ["opentelemetry", "application"],
  "style": "dark",
  "timezone": "browser",
  "panels": [
    {
      "id": 1,
      "title": "HTTP Request Rate",
      "type": "stat",
      "targets": [
        {
          "expr": "rate(http_requests_total[5m])",
          "refId": "A"
        }
      ],
      "fieldConfig": {
        "defaults": {
          "color": {
            "mode": "palette-classic"
          },
          "custom": {
            "displayMode": "list",
            "placement": "bottom"
          },
          "mappings": [],
          "thresholds": {
            "mode": "absolute",
            "steps": [
              {
                "color": "green",
                "value": null
              }
            ]
          }
        }
      },
      "gridPos": {
        "h": 8,
        "w": 12,
        "x": 0,
        "y": 0
      }
    },
    {
      "id": 2,
      "title": "HTTP Response Time",
      "type": "stat",
      "targets": [
        {
          "expr": "histogram_quantile(0.95, rate(http_request_duration_seconds_bucket[5m]))",
          "refId": "A"
        }
      ],
      "fieldConfig": {
        "defaults": {
          "color": {
            "mode": "palette-classic"
          },
          "custom": {
            "displayMode": "list",
            "placement": "bottom"
          },
          "mappings": [],
          "thresholds": {
            "mode": "absolute",
            "steps": [
              {
                "color": "green",
                "value": null
              }
            ]
          },
          "unit": "s"
        }
      },
      "gridPos": {
        "h": 8,
        "w": 12,
        "x": 12,
        "y": 0
      }
    }
  ],
  "time": {
    "from": "now-5m",
    "to": "now"
  },
  "timepicker": {},
  "refresh": "5s",
  "schemaVersion": 27,
  "version": 1,
  "links": []
}